main_ea.py
multiprocess_test.py
EA_components_OhGreat/EA.py
EA_components_OhGreat/Evaluation.py
EA_components_OhGreat/Mutation.py
EA_components_OhGreat/Population.py
EA_components_OhGreat/Recombination.py
EA_components_OhGreat/Selection.py
EA_components_OhGreat/__init__.py
EA_framework_OhGreat-0.3.6.dist-info/LICENSE
EA_framework_OhGreat-0.3.6.dist-info/METADATA
EA_framework_OhGreat-0.3.6.dist-info/WHEEL
EA_framework_OhGreat-0.3.6.dist-info/top_level.txt
EA_framework_OhGreat-0.3.6.dist-info/RECORD
